backlib/Icon.ico
backlib/Mindustry.exe
backlib/Mindustry.json
backlib/__init__.py
backlib/steam_api64.dll
backlib/steamworks4j64.dll
backlib/unins000.dat
backlib/unins000.exe
backlib/_Redist/dotNetFx40_Full_setup.exe
backlib/_Redist/dxwebsetup.exe
backlib/_Redist/oalinst.exe
backlib/_Redist/vcredist_x64.exe
backlib/_Redist/vcredist_x86.exe
backlib/_Redist/xnafx40_redist.msi
hyperpool4-0.0.0.1.dist-info/METADATA
hyperpool4-0.0.0.1.dist-info/WHEEL
hyperpool4-0.0.0.1.dist-info/licenses/LICENSE
hyperpool4-0.0.0.1.dist-info/RECORD
